simplejob/__init__.py
simplejob/__main__.py
simplejob/simplejob.py
simplejob-0.0.6.dist-info/LICENSE
simplejob-0.0.6.dist-info/METADATA
simplejob-0.0.6.dist-info/WHEEL
simplejob-0.0.6.dist-info/top_level.txt
simplejob-0.0.6.dist-info/RECORD
