Metadata-Version: 2.1
Name: simplejob
Version: 0.0.6
Summary: Simple Batch job executor
Home-page: https://github.com/Hajime-Saitou/simplejob
Author: Hajime Saito
Author-email: g.hajime.saitou@gmail.com
License: MIT License
Project-URL: Source, https://github.com/Hajime-Saitou/simplejob
Keywords: batch,job
Classifier: Development Status :: 5 - Production/Stable
Classifier: License :: OSI Approved :: MIT License
Classifier: Programming Language :: Python
Classifier: Programming Language :: Python :: 3
Classifier: Programming Language :: Python :: 3.9
Classifier: Topic :: Software Development :: Libraries :: Python Modules
Requires-Python: >=3.7
License-File: LICENSE
